safe/__init__.py
safe/safe.py
exception_safe-0.0.3.dist-info/LICENSE
exception_safe-0.0.3.dist-info/METADATA
exception_safe-0.0.3.dist-info/WHEEL
exception_safe-0.0.3.dist-info/top_level.txt
exception_safe-0.0.3.dist-info/RECORD
